odoo10_addon_sale_order_ubl-10.0.1.0.0.99.dev9-py2.7-nspkg.pth
odoo/addons/sale_order_ubl/README.rst
odoo/addons/sale_order_ubl/__init__.py
odoo/addons/sale_order_ubl/__manifest__.py
odoo/addons/sale_order_ubl/i18n/es.po
odoo/addons/sale_order_ubl/i18n/pt.po
odoo/addons/sale_order_ubl/i18n/sale_order_ubl.pot
odoo/addons/sale_order_ubl/models/__init__.py
odoo/addons/sale_order_ubl/models/report.py
odoo/addons/sale_order_ubl/models/sale.py
odoo/addons/sale_order_ubl/static/description/icon.png
odoo/addons/sale_order_ubl/tests/__init__.py
odoo/addons/sale_order_ubl/tests/test_ubl_generate.py
odoo10_addon_sale_order_ubl-10.0.1.0.0.99.dev9.dist-info/METADATA
odoo10_addon_sale_order_ubl-10.0.1.0.0.99.dev9.dist-info/RECORD
odoo10_addon_sale_order_ubl-10.0.1.0.0.99.dev9.dist-info/WHEEL
odoo10_addon_sale_order_ubl-10.0.1.0.0.99.dev9.dist-info/namespace_packages.txt
odoo10_addon_sale_order_ubl-10.0.1.0.0.99.dev9.dist-info/top_level.txt
